[
  {
    "@context": "http://www.w3.org/ns/anno.jsonld",
    "type": "Annotation",
    "body": [
      {
        "type": "TextualBody",
        "value": "test",
        "purpose": "commenting"
      }
    ],
    "target": {
      "source": "https://upload.wikimedia.org/wikipedia/commons/7/70/017_Great_blue_turaco_at_Kibale_forest_National_Park_Photo_by_Giles_Laurent.jpg",
      "selector": {
        "type": "FragmentSelector",
        "conformsTo": "http://www.w3.org/TR/media-frags/",
        "value": "xywh=pixel:891.2191772460938,776.7012939453125,738.3370971679688,547.396240234375"
      }
    },
    "id": "#b082de42-ea8c-43c7-b9cc-ddace773bf8c"
  }
]